trompy/__init__.py
trompy/_version.py
trompy/barscatter.py
trompy/fig_utils.py
trompy/general_utils.py
trompy/lick_figs.py
trompy/lick_utils.py
trompy/lickcalc.py
trompy/medfilereader.py
trompy/merge_fed_files.py
trompy/metafile_utils.py
trompy/roc_utils.py
trompy/snipper_class.py
trompy/snipper_utils.py
trompy/stats_utils.py
trompy/trials_figs.py
trompy-0.16.1.dist-info/licenses/LICENSE
trompy-0.16.1.dist-info/licenses/LICENSE.txt
trompy-0.16.1.dist-info/METADATA
trompy-0.16.1.dist-info/WHEEL
trompy-0.16.1.dist-info/top_level.txt
trompy-0.16.1.dist-info/RECORD
