Metadata-Version: 2.4
Name: trompy
Version: 0.16.1
Summary: A collection of tools for data analysis and plotting that originated in the McCutcheon Lab (UiT, Tromso)
Home-page: https://github.com/mccutcheonlab
Download-URL: https://github.com/mccutcheonlab/trompy/archive/v0.16.1.tar.gz
Author: James E McCutcheon
Author-email: James E McCutcheon <j.mccutcheon@uit.no>
License: MIT
Project-URL: Homepage, https://github.com/mccutcheonlab
Project-URL: Repository, https://github.com/mccutcheonlab/trompy
Keywords: neuroscience,behavior
Classifier: Development Status :: 4 - Beta
Classifier: Intended Audience :: Developers
Classifier: Topic :: Software Development :: Build Tools
Classifier: License :: OSI Approved :: MIT License
Classifier: Programming Language :: Python :: 3
Classifier: Programming Language :: Python :: 3.8
Classifier: Programming Language :: Python :: 3.9
Classifier: Programming Language :: Python :: 3.10
Classifier: Programming Language :: Python :: 3.11
Classifier: Programming Language :: Python :: 3.12
Requires-Python: >=3.8
License-File: LICENSE
License-File: LICENSE.txt
Requires-Dist: numpy
Requires-Dist: matplotlib
Requires-Dist: xlrd
Requires-Dist: scipy
Requires-Dist: pandas
Requires-Dist: xlsxwriter
Requires-Dist: tdt
Requires-Dist: openpyxl
Dynamic: author
Dynamic: download-url
Dynamic: home-page
Dynamic: license-file
